deprecated_eolearn_io/__init__.py
eo_learn_io-1.5.0.dist-info/LICENSE
eo_learn_io-1.5.0.dist-info/METADATA
eo_learn_io-1.5.0.dist-info/WHEEL
eo_learn_io-1.5.0.dist-info/top_level.txt
eo_learn_io-1.5.0.dist-info/RECORD
