Metadata-Version: 2.1
Name: eo-learn-io
Version: 1.5.0
Summary: A collection of input/output EOTasks and utilities
Home-page: https://github.com/sentinel-hub/eo-learn
Author: Sinergise EO research team
Author-email: eoresearch@sinergise.com
License: MIT
Project-URL: Documentation, https://eo-learn.readthedocs.io
Project-URL: Source Code, https://github.com/sentinel-hub/eo-learn
Project-URL: Bug Tracker, https://github.com/sentinel-hub/eo-learn/issues
Project-URL: Forum, https://forum.sentinel-hub.com
Platform: UNKNOWN
Classifier: Development Status :: 5 - Production/Stable
Classifier: Intended Audience :: Developers
Classifier: Intended Audience :: Education
Classifier: Intended Audience :: Science/Research
Classifier: License :: OSI Approved :: MIT License
Classifier: Operating System :: MacOS
Classifier: Operating System :: Microsoft :: Windows
Classifier: Operating System :: Unix
Classifier: Programming Language :: Python
Classifier: Programming Language :: Python :: 3
Classifier: Programming Language :: Python :: 3.8
Classifier: Programming Language :: Python :: 3.9
Classifier: Programming Language :: Python :: 3.10
Classifier: Programming Language :: Python :: 3.11
Classifier: Topic :: Scientific/Engineering
Classifier: Topic :: Scientific/Engineering :: GIS
Classifier: Topic :: Scientific/Engineering :: Image Processing
Requires-Python: >=3.8
Requires-Dist: eo-learn
Provides-Extra: meteoblue
Requires-Dist: meteoblue-dataset-sdk (<2,>=1) ; extra == 'meteoblue'
